expstock/__init__.py
expstock/app.py
expstock/conftest.py
expstock/dbconnect.py
expstock/expstock.py
expstock/machine_info.py
expstock/test_dbconnect.py
expstock/test_expstock.py
expstock/template/index.html
expstock/template/params.html
expstock-0.2.data/scripts/expstock-server
expstock-0.2.dist-info/DESCRIPTION.rst
expstock-0.2.dist-info/METADATA
expstock-0.2.dist-info/RECORD
expstock-0.2.dist-info/WHEEL
expstock-0.2.dist-info/metadata.json
expstock-0.2.dist-info/top_level.txt
