Metadata-Version: 2.0
Name: expstock
Version: 0.2
Summary: Stock your experiments
Home-page: https://github.com/chie8842/expstock
Author: Chie Hayashida
Author-email: chie-hayashida@cookpad.com
License: MIT
Platform: UNKNOWN
Classifier: Development Status :: 3 - Alpha
Classifier: Environment :: Console
Classifier: Intended Audience :: Developers
Classifier: License :: OSI Approved :: MIT License
Classifier: Operating System :: OS Independent
Classifier: Programming Language :: Python
Classifier: Programming Language :: Python :: 3
Classifier: Programming Language :: Python :: 3.5
Classifier: Programming Language :: Python :: 3.6
Classifier: Topic :: Software Development :: User Interfaces
Requires-Dist: bottle
